LICENSE
MANIFEST.in
README.md
requirements.txt
setup.py
src/os_m3_engine/VERSION
src/os_m3_engine/__init__.py
src/os_m3_engine/common.py
src/os_m3_engine/launcher.py
src/os_m3_engine/ootb.py
src/os_m3_engine/utils.py
src/os_m3_engine.egg-info/PKG-INFO
src/os_m3_engine.egg-info/SOURCES.txt
src/os_m3_engine.egg-info/dependency_links.txt
src/os_m3_engine.egg-info/not-zip-safe
src/os_m3_engine.egg-info/requires.txt
src/os_m3_engine.egg-info/top_level.txt
src/os_m3_engine/core/__init__.py
src/os_m3_engine/core/backend.py
src/os_m3_engine/core/driver.py
src/os_m3_engine/core/engine.py
src/os_m3_engine/core/frontend.py
src/os_m3_engine/core/othread.py
src/os_m3_engine/core/transport.py
tests/misc.py
tests/test_engine.py
tests/test_launcher.py
tests/test_utils.py